{
  "provision_of_transport": "No",
  "last_updated": "2017-08-24",
  "spark_certified": "No",
  "extended_operating_hours": "No",
  "second_languages_offered": "na",
  "postal_code": "609933",
  "centre_website": "na",
  "saturday": "07:00-14:00",
  "centre_address": "Blk 1A, INTERNATIONAL BUSINESS PARK, #01 - 01, SINGAPORE 609933",
  "n1_vacancy": "No vacancies for the next 1-2 years",
  "infant_vacancy": "No vacancies for the next 1-2 years",
  "government_subsidy": "Yes",
  "organisation_code": "PT",
  "iccp": "No",
  "centre_email_address": "1A@ZOO-PHONICS.COM.SG",
  "centre_code": "PT9179",
  "weekday_halfday_am": "07:00-14:00",
  "weekday_halfday_pm": "14:00-19:00",
  "remarks": "na",
  "scheme_type": "Partner Operator Scheme",
  "weekday_full_day": "07:00-19:00",
  "centre_contact_no": "65701502",
  "k1_vacancy": "No vacancies for the next 1-2 years",
  "food_offered": "No Pork No Lard with No Beef(without Certification from MUIS but from Halal Sources)",
  "pg_vacancy": "No vacancies for the next 1-2 years",
  "n2_vacancy": "No vacancies for the next 1-2 years",
  "gst_regisration": "No",
  "centre_name": "SAFARI HOUSE BABIES & TODDLERS",
  "organisation_description": "PRIVATE",
  "k2_vacancy": "No vacancies for the next 1-2 years",
  "id": "PT9179",
  "service_listing": [
    {
      "age_to": "83",
      "levels_offered": "Child Care Programme",
      "last_updated": "2016-03-18",
      "programmes_offered": "Child Full Day",
      "fees": "800",
      "remarks": "$1350 for SPR and Foreigners",
      "age_from": "18"
    },
    {
      "age_to": "83",
      "levels_offered": "Child Care Programme",
      "last_updated": "2016-03-18",
      "programmes_offered": "Child Half-Day AM",
      "fees": "600",
      "remarks": "$990 for SPR and Foreigners",
      "age_from": "18"
    },
    {
      "age_to": "83",
      "levels_offered": "Child Care Programme",
      "last_updated": "2016-03-18",
      "programmes_offered": "Child Half-Day PM",
      "fees": "600",
      "remarks": "$990 for SPR and Foreigners",
      "age_from": "18"
    },
    {
      "age_to": "18",
      "levels_offered": "Infant Care Programme",
      "last_updated": "2016-03-18",
      "programmes_offered": "Infant Full Day",
      "fees": "1400",
      "remarks": "$1600 for SPR and Foreigners",
      "age_from": "3"
    },
    {
      "age_to": "18",
      "levels_offered": "Infant Care Programme",
      "last_updated": "2016-08-22",
      "programmes_offered": "Infant Full Day",
      "fees": "1400",
      "remarks": "na",
      "age_from": "2"
    },
    {
      "age_to": "18",
      "levels_offered": "Infant Care Programme",
      "last_updated": "2016-03-18",
      "programmes_offered": "Infant Half-Day AM",
      "fees": "1000",
      "remarks": "$1130 for SPR and Foreigners",
      "age_from": "3"
    },
    {
      "age_to": "18",
      "levels_offered": "Infant Care Programme",
      "last_updated": "2016-03-18",
      "programmes_offered": "Infant Half-Day PM",
      "fees": "1000",
      "remarks": "$1130 for SPR and Foreigners",
      "age_from": "3"
    }
  ],
  "license_history": [
    {
      "license_issue_date": "2016-08-31",
      "license_tenure": "24"
    },
    {
      "license_issue_date": "2015-08-31",
      "license_tenure": "12"
    }
  ],
  "incidental_charges": [
    {
      "incidental_charges": "Registration Fee",
      "amount": "214",
      "frequency": "Ad-hoc"
    },
    {
      "incidental_charges": "Uniform",
      "amount": "64.2",
      "frequency": "Ad-hoc"
    },
    {
      "incidental_charges": "DEPOSIT",
      "amount": "1350",
      "frequency": "Ad-hoc"
    },
    {
      "incidental_charges": "PVC Mattress(Optional)",
      "amount": "117.7",
      "frequency": "Ad-hoc"
    }
  ],
  "svy21": [
    18542.4785000002,
    34473.46539999917
  ],
  "coordinates": [
    103.74833757502732,
    1.3280388261223552
  ],
  "planning_area": "JE"
}