{
  "provision_of_transport": false,
  "last_updated": "2017-11-03",
  "spark_certified": false,
  "extended_operating_hours": false,
  "second_languages_offered": null,
  "postal_code": "819663",
  "centre_website": null,
  "saturday": "07:00-14:00",
  "centre_address": "65, AIRPORT BOULEVARD, #03 - 22-29, CHANGI AIRPORT TERMINAL 3, SINGAPORE 819663",
  "n1_vacancy": "No vacancies for the next 1-2 years",
  "infant_vacancy": "No vacancies for the next 1-2 years",
  "government_subsidy": true,
  "organisation_code": "PT",
  "iccp": false,
  "centre_email_address": "SUFANGNG@MINDCHAMPS.ORG",
  "centre_code": "PT9306",
  "weekday_halfday_am": "07:00-13:00",
  "weekday_halfday_pm": "13:00-19:00",
  "remarks": null,
  "scheme_type": null,
  "weekday_full_day": "07:00-19:00",
  "centre_contact_no": "62410100",
  "k1_vacancy": "No vacancies for the next 1-2 years",
  "food_offered": "Halal Food with No Beef(with Certification from MUIS)",
  "pg_vacancy": "No vacancies for the next 1-2 years",
  "n2_vacancy": "No vacancies for the next 1-2 years",
  "gst_regisration": true,
  "centre_name": "MINDCHAMPS PRESCHOOL @ CHANGI AIRPORT PTE LTD",
  "organisation_description": "PRIVATE",
  "k2_vacancy": "No vacancies for the next 1-2 years",
  "id": "PT9306",
  "service_listing": [
    {
      "age_to": "35",
      "levels_offered": "Child Care Programme",
      "last_updated": "2016-10-29",
      "programmes_offered": "Child Full Day",
      "fees": "1904.6",
      "remarks": "na",
      "age_from": "18"
    },
    {
      "age_to": "83",
      "levels_offered": "Child Care Programme",
      "last_updated": "2016-10-29",
      "programmes_offered": "Child Full Day",
      "fees": "1797.6",
      "remarks": "na",
      "age_from": "36"
    },
    {
      "age_to": "35",
      "levels_offered": "Child Care Programme",
      "last_updated": "2016-10-29",
      "programmes_offered": "Child Half-Day AM",
      "fees": "1690.6",
      "remarks": "na",
      "age_from": "18"
    },
    {
      "age_to": "83",
      "levels_offered": "Child Care Programme",
      "last_updated": "2016-10-29",
      "programmes_offered": "Child Half-Day AM",
      "fees": "1583.6",
      "remarks": "na",
      "age_from": "36"
    }
  ],
  "license_history": [
    {
      "license_issue_date": "2017-10-29",
      "license_tenure": "6"
    },
    {
      "license_issue_date": "2016-10-29",
      "license_tenure": "12"
    }
  ],
  "incidental_charges": [
    {
      "incidental_charges": "Deposit",
      "amount": "1797.6",
      "frequency": "Ad-hoc"
    },
    {
      "incidental_charges": "Deposit",
      "amount": "1904.6",
      "frequency": "Ad-hoc"
    },
    {
      "incidental_charges": "INSURANCE (OPTIONAL)",
      "amount": "6.4",
      "frequency": "Annual"
    },
    {
      "incidental_charges": "UNIFORM",
      "amount": "58.85",
      "frequency": "Annual"
    },
    {
      "incidental_charges": "Deposit",
      "amount": "1583.6",
      "frequency": "Ad-hoc"
    },
    {
      "incidental_charges": "Deposit",
      "amount": "1690.6",
      "frequency": "Ad-hoc"
    },
    {
      "incidental_charges": "REGISTRATION FEE",
      "amount": "460.1",
      "frequency": "Ad-hoc"
    }
  ],
  "svy21": [
    45054.2735961135,
    37634.8765231278
  ],
  "coordinates": [
    103.986562208495,
    1.35662609413491
  ],
  "planning_area": "CH"
}