{
  "provision_of_transport": false,
  "last_updated": "2017-11-15",
  "spark_certified": false,
  "extended_operating_hours": false,
  "second_languages_offered": null,
  "postal_code": "519599",
  "centre_website": null,
  "saturday": "07:00-14:00",
  "centre_address": "1, PASIR RIS CLOSE, #03 - 113, E!HUB@DOWNTOWN EAST, SINGAPORE 519599",
  "n1_vacancy": "No vacancies for the next 1-2 years",
  "infant_vacancy": "No vacancies for the next 1-2 years",
  "government_subsidy": true,
  "organisation_code": "PT",
  "iccp": false,
  "centre_email_address": "FELICIA.YAN@LITTLESKOOLHOUSE.COM",
  "centre_code": "PT9287",
  "weekday_halfday_am": "07:00-13:00",
  "weekday_halfday_pm": "13:00-19:00",
  "remarks": null,
  "scheme_type": null,
  "weekday_full_day": "07:00-19:00",
  "centre_contact_no": "65855292",
  "k1_vacancy": "No vacancies for the next 1-2 years",
  "food_offered": "No Pork No Lard with No Beef(without Certification from MUIS but from Halal Sources)",
  "pg_vacancy": "No vacancies for the next 1-2 years",
  "n2_vacancy": "No vacancies for the next 1-2 years",
  "gst_regisration": true,
  "centre_name": "THE LITTLE SKOOL- HOUSE INTERNATIONAL PTE LTD",
  "organisation_description": "PRIVATE",
  "k2_vacancy": "No vacancies for the next 1-2 years",
  "id": "PT9287",
  "service_listing": [
    {
      "age_to": "83",
      "levels_offered": "Child Care Programme",
      "last_updated": "2017-01-01",
      "programmes_offered": "Child Full Day",
      "fees": "1583.6",
      "remarks": "Amount inclusive of GST",
      "age_from": "18"
    },
    {
      "age_to": "83",
      "levels_offered": "Child Care Programme",
      "last_updated": "2017-01-01",
      "programmes_offered": "Child Half-Day AM",
      "fees": "1209.1",
      "remarks": "Amount inclusive of GST",
      "age_from": "18"
    },
    {
      "age_to": "18",
      "levels_offered": "Infant Care Programme",
      "last_updated": "2017-01-01",
      "programmes_offered": "Infant Full Day",
      "fees": "2086.5",
      "remarks": "Amount inclusive of GST",
      "age_from": "2"
    }
  ],
  "license_history": [
    {
      "license_issue_date": "2017-07-25",
      "license_tenure": "24"
    },
    {
      "license_issue_date": "2016-07-25",
      "license_tenure": "12"
    }
  ],
  "incidental_charges": [
    {
      "incidental_charges": "Deposit",
      "amount": "2033",
      "frequency": "Ad-hoc"
    },
    {
      "incidental_charges": "Deposit",
      "amount": "1476.6",
      "frequency": "Ad-hoc"
    },
    {
      "incidental_charges": "Uniform",
      "amount": "22.47",
      "frequency": "Ad-hoc"
    },
    {
      "incidental_charges": "Deposit",
      "amount": "1155.6",
      "frequency": "Ad-hoc"
    },
    {
      "incidental_charges": "Registration Fee",
      "amount": "321",
      "frequency": "Ad-hoc"
    },
    {
      "incidental_charges": "Deposit",
      "amount": "1583.6",
      "frequency": "Ad-hoc"
    },
    {
      "incidental_charges": "Deposit",
      "amount": "2086.5",
      "frequency": "Ad-hoc"
    }
  ],
  "svy21": [
    41591.12,
    40122.74
  ],
  "coordinates": [
    103.9554448,
    1.3791272
  ],
  "planningArea": "PR",
  "neighbours": [
    "PL",
    "PG",
    "SE",
    "CH",
    "TM"
  ]
}