{
	"Halal Food with Beef(with Certification from MUIS)": 6,
	"Halal Food with No Beef(with Certification from MUIS)": 47,
	"No Pork No Lard with Beef(from Non Halal Sources)": 24,
	"No Pork No Lard with Beef(without Certification from MUIS but from Halal Sources)": 121,
	"No Pork No Lard with No Beef(from Non Halal Sources)": 263,
	"No Pork No Lard with No Beef(without Certification from MUIS but from Halal Sources)": 895,
	"Other: Catering for allergies+ specific food requirements": 1,
	"Other: Centre serves Minced meat(pork) porridge, which the Japanese parents have requested for.": 1,
	"Other: Chicken, Fish, Soy Bean Products, Vegetables": 1,
	"Other: Food served is non-halal.": 1,
	"Other: Halal Food with Beef (certification is not required as it is a Muslim Assoication)": 1,
	"Other: NIL": 1,
	"Other: Non-Halal for non-Muslim student": 1,
	"Other: PORK": 1,
	"Other: PORK, CHICKEN, EGGS AND VEGETABLES": 1,
	"Other: PORK,CHICKEN": 1,
	"Other: Pork": 2,
	"Other: Pork - Char Siew, chicken etc.": 1,
	"Other: Pork with no beef": 1,
	"Other: Pork, Chicken & Fish": 1,
	"Other: fish, chicken, vegetables, milk, bread": 1,
	"Other: pork, chicken, duck, fish, prawn": 1,
	"Vegetarian": 20,
	"na": 16
}