{
	"name": "HONG PLASTIC SURGERY",
	"tel": "63396210",
	"fax": "63396240",
	"licensee": "HONG PLASTIC SURGERY PTE. LTD",
	"licensePeriod": "25/03/2016 to 24/03/2018",
	"licenseClass": "[ 2 Years ( 2A ) ]",
	"hciCode": "14M0061",
	"address": "38 IRRAWADDY ROAD, Mt Elizabeth Novena Specialist Centre, #10-38 Singapore 329563",
	"doctorInCharge": [
		{
			"name": "Hong Soo Wan",
			"qualifications": [
				"MBBS (National University of Singapore, Singapore) 1986",
				"FRCS (Royal College of Physicians and Surgeons of Glasgow, United Kingdom) 1992",
				"FAMS (Plastic Surg) (Academy of Medicine, Singapore) 1998"
			],
			"specialties": [
				"Plastic Surgery"
			]
		}
	],
	"detailedServices": {
		"Specialist Medical": [
			"Plastic Surgery"
		]
	},
	"operatingHours": {
		"Monday": "09:00 am to 01:00 pm, 02:00 pm to 05:00 pm",
		"Tuesday": "09:00 am to 01:00 pm, 02:00 pm to 05:00 pm",
		"Wednesday": "09:00 am to 01:00 pm, 02:00 pm to 05:00 pm",
		"Thursday": "09:00 am to 01:00 pm, 02:00 pm to 05:00 pm",
		"Friday": "09:00 am to 01:00 pm, 02:00 pm to 05:00 pm",
		"Saturday": "09:00 am to 01:00 pm",
		"Sunday": "Closed",
		"Public Holiday": "Closed"
	},
	"id": "14M0061",
	"coordinates": [
		103.8442263,
		1.3221466
	],
	"svy21": [
		29213.92,
		33821.77
	],
	"planningArea": "NV",
	"neighbours": [
		"BT",
		"KL",
		"CC",
		"TN",
		"TP",
		"CA"
	]
}