{
	"name": "TWIN CITY ENDODONTICS (TANGLIN)",
	"tel": "62353063",
	"fax": "67347515",
	"licensee": "TWIN CITY ENDODONTICS PTE. LTD.",
	"licensePeriod": "09/04/2017 to 08/04/2019",
	"licenseClass": "[ 2 Years ( 2A ) ]",
	"hciCode": "17D0098",
	"address": "19 TANGLIN ROAD, TANGLIN SHOPPING CENTRE, #06-20/21 Singapore 247909",
	"doctorInCharge": [
		{
			"name": "Ang Ee Choon Richard",
			"qualifications": [
				"BDS (National University of Singapore, Singapore) 1999",
				"MRDRCS (Edinburgh) (Royal College of Surgeons of Edinburgh, United Kingdom) 2005",
				"MDS (National University of Singapore, Singapore) 2005"
			],
			"specialties": [
				"Endodontics"
			]
		}
	],
	"detailedServices": {
		"General Dental": true,
		"Specialist Dental": [
			"Endodontics"
		]
	},
	"id": "17D0098",
	"coordinates": [
		103.8270506,
		1.3064027
	],
	"svy21": [
		27302.43,
		32080.89
	],
	"planningArea": "CA",
	"neighbours": [
		"BM",
		"KL",
		"MP",
		"NV",
		"TN"
	]
}