{
	"name": "GYNAE HEALTH CLINIC FOR WOMEN PTE LTD",
	"tel": "62828960",
	"fax": "62826106",
	"licensee": "Phua Soo Mear",
	"licensePeriod": "03/12/2014 to 31/01/2019",
	"licenseClass": "[ < 1 Year ]",
	"hciCode": "9400624",
	"address": "BLK 211 Hougang St 21, #01-289 Singapore 530211",
	"doctorInCharge": [
		{
			"name": "Phua Soo Mear",
			"qualifications": [
				"MBBS (National University of Singapore, Singapore) 1983",
				"MRCOG (Royal College of Obstetricians and Gynaecologists, United Kingdom) 1989",
				"FAMS (O&G) (Academy of Medicine, Singapore) 1993"
			],
			"specialties": [
				"Obstetrics & Gynaecology"
			]
		}
	],
	"detailedServices": {
		"Specialist Medical": [
			"Obstetrics & Gynaecology"
		]
	},
	"id": "9400624",
	"coordinates": [
		103.8877173,
		1.3596229
	],
	"svy21": [
		34053.95,
		37965.78
	],
	"planningArea": "HG",
	"neighbours": [
		"BD",
		"GL",
		"PL",
		"SE",
		"SG",
		"TP"
	]
}