{
	"name": "INTERNATIONAL WOMEN'S CLINIC",
	"tel": "63335550",
	"fax": "65343326",
	"licensee": "ANG HUAI YAN",
	"licensePeriod": "23/04/2016 to 22/04/2021",
	"licenseClass": "[ 5 Years ]",
	"hciCode": "9403044",
	"address": "24 RAFFLES PLACE, CLIFFORD CENTRE, #02-08 Singapore 048621",
	"doctorInCharge": [
		{
			"name": "ANG HUAI YAN",
			"qualifications": [
				"MBBS (National University of Singapore, Singapore) 1990",
				"MRANZCOG (Royal Australian and New Zealand College of O & G, Australia) 1997",
				"M Med (O&G) (National University of Singapore, Singapore) 1997"
			],
			"specialties": [
				"Obstetrics & Gynaecology"
			]
		}
	],
	"detailedServices": {
		"Specialist Medical": [
			"Obstetrics & Gynaecology"
		]
	},
	"id": "9403044",
	"coordinates": [
		103.8521303,
		1.2838559
	],
	"svy21": [
		30093.59,
		29587.79
	],
	"planningArea": "CA",
	"neighbours": [
		"BM",
		"KL",
		"MP",
		"NV",
		"TN"
	]
}