{
	"name": "INTERNATIONAL MEDICAL CLINIC",
	"tel": "68874440",
	"fax": "69974441",
	"licensee": "TMVC SINGAPORE PTE LTD",
	"licensePeriod": "01/05/2017 to 28/01/2019",
	"licenseClass": "[ 5 Years ]",
	"hciCode": "9405465",
	"address": "1 ORCHARD BOULEVARD, CAMDEN MEDICAL CENTRE, #11-06/07 Singapore 248649",
	"doctorInCharge": [
		{
			"name": "CLARICE SOEK-YIN CHIA WOODWORTH",
			"qualifications": [
				"MBBS (National University of Singapore, Singapore) 1993",
				"Dip Pract Derm (University of Wales, United Kingdom) 1999"
			],
			"specialties": [
				"Family Physician"
			]
		}
	],
	"detailedServices": {
		"General Medical": true,
		"Specialist Medical": [
			"Paediatric Medicine"
		]
	},
	"operatingHours": {
		"Public Holiday": "Closed",
		"Monday": "09:00 am to 05:30 pm",
		"Tuesday": "09:00 am to 05:30 pm",
		"Wednesday": "09:00 am to 05:30 pm",
		"Thursday": "09:00 am to 05:30 pm",
		"Friday": "09:00 am to 05:30 pm",
		"Saturday": "09:00 am to 01:00 pm",
		"Sunday": "Closed"
	},
	"id": "9405465",
	"coordinates": [
		103.8239072,
		1.3031376
	],
	"svy21": [
		26952.59,
		31719.85
	],
	"planningArea": "CA",
	"neighbours": [
		"BM",
		"KL",
		"MP",
		"NV",
		"TN"
	]
}