{
	"name": "LEONG EYE CLINIC & SURGERY",
	"tel": "67340325",
	"fax": "67340326",
	"licensee": "LEONG SEEK KEE",
	"licensePeriod": "01/01/2014 to 31/12/2018",
	"licenseClass": "[ 5 Years ]",
	"hciCode": "9400936",
	"address": "304 ORCHARD ROAD, LUCKY PLAZA, #06-43 Singapore 238863",
	"doctorInCharge": [
		{
			"name": "LEONG SEEK KEE",
			"qualifications": [
				"MBBS (University of Malaya, Singapore) 1961",
				"DO (Ophth) (Royal College of Surgeons of Edinburgh, United Kingdom) 1967",
				"FRCSEd (Ophth) (Royal College of Surgeons of Edinburgh, United Kingdom) 1971",
				"FAMS (Academy of Medicine, Singapore) 1974"
			],
			"specialties": [
				"Ophthalmology"
			]
		}
	],
	"detailedServices": {
		"Specialist Medical": [
			"Ophthalmology"
		]
	}
}