{
	"name": "MEDEN CLINIC & SURGERY",
	"tel": "62713586",
	"fax": "62713586",
	"licensee": "CHANG HAU SENG",
	"licensePeriod": "01/01/2016 to 31/12/2017",
	"licenseClass": "[ 2 Years ( 2D ) ]",
	"hciCode": "9401066",
	"address": "BLK 35 TELOK BLANGAH RISE, #01-295 Singapore 090035",
	"doctorInCharge": [
		{
			"name": "CHANG HAU SENG",
			"qualifications": [
				"MBBS (University of Singapore, Singapore) 1975"
			],
			"specialties": []
		}
	],
	"detailedServices": {
		"General Medical": true
	},
	"operatingHours": {
		"Public Holiday": "Closed",
		"Monday and Tuesday": "09:15 am to 12:00 pm, 02:00 pm to 05:00 pm, 07:00 pm to 08:30 pm",
		"Wednesday to Friday": "09:15 am to 12:00 pm, 02:00 pm to 05:00 pm",
		"Saturday": "09:15 am to 12:00 pm, 02:00 pm to 04:00 pm",
		"Sunday": "09:15 am to 12:00 pm"
	}
}