{
	"name": "ALEXIUS CHEE GASTROENTEROLOGY & MEDICAL CLINIC",
	"tel": "65358833",
	"fax": "62352389",
	"licensee": "Chee Eng Nam Alexius",
	"licensePeriod": "03/03/2015 to 02/03/2020",
	"licenseClass": "[ 5 Years ]",
	"hciCode": "9403897",
	"address": "3 Mount Elizabeth, Mount Elizabeth Medical Centre, #05-09 Singapore 228510",
	"doctorInCharge": [
		{
			"name": "Chee Eng Nam Alexius",
			"qualifications": [
				"MBBS (University of Singapore, Singapore) 1980",
				"M Med (Int Med) (National University of Singapore, Singapore) 1986",
				"FAMS (Gastroenterology) (Academy of Medicine, Singapore) 1992"
			],
			"specialties": [
				"Gastroenterology"
			]
		}
	],
	"detailedServices": {
		"General Medical": true,
		"Specialist Medical": [
			"Gastroenterology"
		]
	},
	"operatingHours": {
		"Monday to Friday": "09:00 am to 04:30 pm"
	}
}