{
	"name": "THAM SIEW NEE SKIN CLINIC",
	"tel": "64766821",
	"fax": "64764552",
	"licensee": "SKIN HEALTH SINGAPORE PTE. LTD.",
	"licensePeriod": "26/03/2014 to 25/03/2019",
	"licenseClass": "[ 5 Years ]",
	"hciCode": "9401660",
	"address": "6 NAPIER RD, GLENEAGLES MEDICAL CENTRE, #07-08 Singapore 258499",
	"doctorInCharge": [
		{
			"name": "THAM SIEW NEE",
			"qualifications": [
				"MBBS (University of Adelaide, Australia) 1974",
				"M Med (Int Med) (National University of Singapore, Singapore) 1980",
				"FAMS (Derm) (Academy of Medicine, Singapore) 1985"
			],
			"specialties": [
				"Dermatology"
			]
		}
	],
	"detailedServices": {
		"Specialist Medical": [
			"Dermatology"
		]
	},
	"operatingHours": {
		"Saturday": "08:30 am to 01:00 pm"
	}
}