{
	"name": "FAMILY DOCTORS AT 365",
	"tel": "62652968",
	"fax": "62652968",
	"licensee": "Lee Chun Fai",
	"licensePeriod": "08/10/2017 to 07/10/2022",
	"licenseClass": "[ 5 Years ]",
	"hciCode": "9404579",
	"address": "BLK 365 CORPORATION DRIVE, #01-407 Singapore 610365",
	"doctorInCharge": [
		{
			"name": "Lee Chun Fai",
			"qualifications": [
				"MBBS (National University of Singapore, Singapore) 1986"
			],
			"specialties": [
				"Family Physician"
			]
		}
	],
	"detailedServices": {
		"General Medical": true
	},
	"programmes": [
		"Chronic Disease Management Programme (CDMP)",
		"Community Health Assistance Scheme (CHAS)"
	],
	"operatingHours": {
		"Monday to Friday": "08:30 am to 12:30 pm, 02:00 pm to 05:00 pm, 06:30 pm to 09:00 pm",
		"Saturday": "08:30 am to 12:30 pm, 06:30 pm to 09:00 pm",
		"Sunday": "08:30 am to 12:00 pm"
	}
}