{
	"name": "THOMSON WOMEN CANCER CENTRE",
	"tel": "65918218",
	"fax": "65918210",
	"licensee": "THOMSON WOMEN CANCER CENTRE PTE. LTD.",
	"licensePeriod": "27/02/2015 to 26/02/2020",
	"licenseClass": "[ 5 Years ]",
	"hciCode": "9405107",
	"address": "10 SINARAN DRIVE, SQUARE 2, NOVENA MEDICAL CENTER, #09-15/16 Singapore 307506",
	"doctorInCharge": [
		{
			"name": "Tay Eng Hseon",
			"qualifications": [
				"MBBS (National University of Singapore, Singapore) 1987",
				"M Med (O&G) (National University of Singapore, Singapore) 1993",
				"MRACOG (Royal Australian College of Obstetricians and Gynaecologists, Australia) 1993",
				"MRCOG (Royal College of Obstetricians and Gynaecologists, United Kingdom) 1993",
				"Dip (Gynaecological Oncology) (Royal Australian and New Zealand College of O & G, Australia) 1999",
				"FAMS (Academy of Medicine, Singapore) 1999"
			],
			"specialties": [
				"Obstetrics & Gynaecology"
			]
		}
	],
	"detailedServices": {
		"Specialist Medical": [
			"General Surgery",
			"Medical Oncology",
			"Obstetrics & Gynaecology"
		]
	},
	"operatingHours": {
		"Monday to Friday": "08:30 am to 05:30 pm",
		"Saturday to Saturday": "08:30 am to 12:30 pm",
		"Sunday and Public Holiday": "Closed"
	}
}