{
	"name": "THE DUBLIN CLINIC",
	"tel": "67747300",
	"fax": "67785311",
	"licensee": "DUBLIN CLINIC PTE. LTD.",
	"licensePeriod": "29/01/2014 to 28/01/2019",
	"licenseClass": "[ 5 Years ]",
	"hciCode": "9405467",
	"address": "BLK 109 CLEMENTI STREET 11, #01-25 Singapore 120109",
	"doctorInCharge": [
		{
			"name": "Teo Yi Jin",
			"qualifications": [
				"MB BCh (National University of Ireland, Ireland) 1997"
			],
			"specialties": [
				"Family Physician"
			]
		}
	],
	"detailedServices": {
		"General Medical": true
	},
	"programmes": [
		"Chronic Disease Management Programme (CDMP)"
	],
	"operatingHours": {
		"Public Holiday": "Closed",
		"Monday to Thursday": "08:00 am to 01:00 pm, 05:00 pm to 08:00 pm",
		"Friday": "08:00 am to 01:00 pm",
		"Saturday": "10:00 am to 01:00 pm",
		"Sunday": "05:00 pm to 08:00 pm"
	}
}