{
	"name": "DERMCLEAR AESTHETIC & LASER CLINIC",
	"tel": "63565005",
	"fax": "63565115",
	"licensee": "Derm Clear Aesthetic & Laser Clinic Pte. Ltd.",
	"licensePeriod": "07/09/2014 to 06/09/2019",
	"licenseClass": "[ 5 Years ]",
	"hciCode": "9405694",
	"address": "1 GRANGE ROAD, ORCHARD BUILDING, #10-03 Singapore 239693",
	"doctorInCharge": [
		{
			"name": "Chin Yee Choong",
			"qualifications": [
				"MBBS (National University of Singapore, Singapore) 1988"
			],
			"specialties": []
		}
	],
	"detailedServices": {
		"General Medical": true
	},
	"operatingHours": {
		"Monday to Friday": "10:30 am to 07:00 pm",
		"Sunday and Public Holiday": "Closed"
	}
}