{
	"name": "MICHAEL HOE SURGERY GASTROINTESTINAL SURGERY, HEPATOBILIARY & PANCREATIC SURGERY, LAPAROSCOPIC SURGERY",
	"tel": "64790700",
	"fax": "64790701",
	"licensee": "MICHAEL HOE SURGERY PTE. LTD.",
	"licensePeriod": "29/04/2015 to 28/04/2020",
	"licenseClass": "[ 5 Years ]",
	"hciCode": "11C0053",
	"address": "6 Napier Road, Gleneagles Medical Centre, #07-19 Singapore 258499",
	"doctorInCharge": [
		{
			"name": "Hoe Nan Yuh",
			"qualifications": [
				"MBBS (University of Singapore, Singapore) 1978",
				"FRCSEd (Gen Surg) (Royal College of Surgeons of Edinburgh, United Kingdom) 1985",
				"FAMS (Gen Surg) (Academy of Medicine, Singapore) 1994"
			],
			"specialties": [
				"General Surgery"
			]
		}
	],
	"detailedServices": {
		"Specialist Medical": [
			"General Surgery"
		]
	}
}