{
	"name": "THOMSON SPECIALIST DENTISTRY",
	"tel": "62551771",
	"fax": "66817790",
	"licensee": "THOMSON DENTAL CENTRE PTE. LTD.",
	"licensePeriod": "15/01/2016 to 14/01/2018",
	"licenseClass": "[ 2 Years ( 2A ) ]",
	"hciCode": "11C0236",
	"address": "8 SINARAN DRIVE, NOVENA SPECIALIST CENTER, #06-04/05/06/07 Singapore 307470",
	"doctorInCharge": [
		{
			"name": "Aidan Yeo Choon Poh",
			"qualifications": [
				"BDS (National University of Singapore, Singapore) 1997",
				"MDS (Oral & Maxillofacial Surgery) (Singapore) (National University of Singapore, Singapore) 2002",
				"FAMS (Oral & Maxillofacial Surgery) (Academy of Medicine, Singapore, Singapore) 2005"
			],
			"specialties": [
				"Oral & Maxillo-Facial Surgery"
			]
		}
	],
	"detailedServices": {
		"Specialist Dental": [
			"Endodontics",
			"Oral & Maxillo-Facial Surgery",
			"Orthodontics",
			"Prosthodontics"
		]
	},
	"operatingHours": {
		"Monday to Friday": "09:00 am to 07:00 pm",
		"Saturday": "09:00 am to 02:00 pm"
	}
}