{
	"name": "ORTHOPAEDIC AND SPINE CLINIC PTE. LTD.",
	"tel": "62355774",
	"fax": "62355716",
	"licensee": "ORTHOPAEDIC AND SPINE CLINIC PTE. LTD.",
	"licensePeriod": "07/09/2017 to 06/09/2019",
	"licenseClass": "[ 2 Years ( 2A ) ]",
	"hciCode": "12C0207",
	"address": "3 MOUNT ELIZABETH, MOUNT ELIZABETH MEDICAL CENTRE, #13-06 Singapore 228510",
	"doctorInCharge": [
		{
			"name": "Tow Phak Boon Benjamin",
			"qualifications": [
				"MBBS (National University of Singapore, Singapore) 1998",
				"MRCS (Royal College of Surgeons of Edinburgh, United Kingdom) 2001",
				"M Med (Ortho Surg) (National University of Singapore, Singapore) 2002",
				"FRCS (Orth Surg) (Royal College of Surgeons of Edinburgh, United Kingdom) 2006"
			],
			"specialties": [
				"Orthopaedic Surgery"
			]
		}
	],
	"detailedServices": {
		"Specialist Medical": [
			"Orthopaedic Surgery"
		]
	},
	"operatingHours": {
		"Monday to Friday": "09:00 am to 05:00 pm",
		"Saturday": "09:00 am to 01:00 pm"
	}
}