{
	"name": "NOBEL ENT HEAD, NECK & THYROID  SURGERY CENTRE",
	"tel": "62516630",
	"fax": "62516631",
	"licensee": "HEALTHWAY MEDICAL ENTERPRISES PTE LTD",
	"licensePeriod": "29/06/2016 to 28/06/2018",
	"licenseClass": "[ 2 Years ( 2A ) ]",
	"hciCode": "13M0262",
	"address": "820 THOMSON ROAD, MOUNT ALVERNIA HOSPITAL, #05-01 Singapore 574623",
	"doctorInCharge": [
		{
			"name": "Hobbs Christopher Geoffrey Laurence",
			"qualifications": [
				"MBBS (Imperial College of Science, Technology and Medicine, United Kingdom) 1996",
				"BSc (Pathology with Basic Med Sci) (University of London, United Kingdom) 1995",
				"MRCS (Royal College of Surgeons of England, United Kingdom) 2000",
				"FRCS (Royal College of Surgeons of England, United Kingdom) 2007"
			],
			"specialties": [
				"Otorhinolaryngology"
			]
		}
	],
	"detailedServices": {
		"Specialist Medical": [
			"Otorhinolaryngology"
		]
	}
}