{
	"name": "DOCTORS FOR LIFE MEDICAL",
	"tel": "69090527",
	"fax": "63869298",
	"licensee": "TS MEDICAL PTE. LTD.",
	"licensePeriod": "22/04/2017 to 21/04/2019",
	"licenseClass": "[ 2 Years ( 2A ) ]",
	"hciCode": "17M0113",
	"address": "3 PICKERING STREET, NANKIN ROW, #01-02 Singapore 048660",
	"doctorInCharge": [
		{
			"name": "Justin Sim Jit Weng",
			"qualifications": [
				"MB ChB (University of Bristol, United Kingdom) 2008"
			],
			"specialties": []
		}
	],
	"detailedServices": {
		"General Medical": true
	},
	"programmes": [
		"Chronic Disease Management Programme (CDMP)"
	],
	"operatingHours": {
		"Monday to Friday": "08:30 am to 05:00 pm",
		"Saturday": "09:00 am to 01:00 pm"
	}
}