{
	"name": "DENTAL CLINIC",
	"tel": "68962916",
	"fax": "68962916",
	"licensee": "Health Promotion Board",
	"licensePeriod": "31/01/2015 to 30/01/2020",
	"licenseClass": "[ 5 Years ]",
	"hciCode": "9403852",
	"address": "90 BUKIT BATOK EAST AVENUE 6,, KEMING PRIMARY SCHOOL, Singapore 659762",
	"doctorInCharge": [
		{
			"name": "Tham Sai Soo",
			"qualifications": [
				"BDS (University of Singapore, Singapore) 1976"
			],
			"specialties": []
		}
	],
	"detailedServices": {
		"General Dental": true
	},
	"operatingHours": {
		"Monday to Thursday": "08:00 am to 05:30 pm",
		"Friday and Friday": "08:00 am to 05:00 pm"
	}
}