{
	"name": "PINNACLE JOINT & SPORTS CENTRE",
	"tel": "67370558",
	"fax": "67370522",
	"licensee": "PINNACLE JOINT & SPORTS CENTRE PTE. LTD.",
	"licensePeriod": "21/06/2017 to 20/06/2022",
	"licenseClass": "[ 5 Years ]",
	"hciCode": "13C0152",
	"address": "3 MOUNT ELIZABETH, MOUNT ELIZABETH MEDICAL CENTRE, #04-07 Singapore 228510",
	"doctorInCharge": [
		{
			"name": "Kevin Lee Boon Leng",
			"qualifications": [
				"MBBS (National University of Singapore, Singapore) 1996",
				"MRCSEd (Royal College of Surgeons of Edinburgh, United Kingdom) 2001",
				"M Med (Ortho Surg) (National University of Singapore, Singapore) 2002",
				"FRCS (Orth Surg) (Royal College of Surgeons of Edinburgh, United Kingdom) 2006"
			],
			"specialties": [
				"Orthopaedic Surgery"
			]
		}
	],
	"detailedServices": {
		"Specialist Medical": [
			"Diagnostic Radiology",
			"Orthopaedic Surgery"
		]
	},
	"id": "13C0152",
	"coordinates": [
		103.8354393,
		1.3051652
	],
	"svy21": [
		28236.02,
		31944.06
	],
	"planningArea": "CA",
	"neighbours": [
		"BM",
		"KL",
		"MP",
		"NV",
		"TN"
	]
}