{
	"name": "RENAL LIFE (ALEXANDRA) DIALYSIS CENTRE PTE LTD",
	"tel": "62747084",
	"fax": "62719478",
	"licensee": "RENAL LIFE (ALEXANDRA) DIALYSIS CENTRE PTE. LTD.",
	"licensePeriod": "05/09/2017 to 04/09/2019",
	"licenseClass": "[ 2 Years ( 2C ) ]",
	"hciCode": "14M0270",
	"address": "BLK 123 BUKIT MERAH LANE 1, #01-74 Singapore 150123",
	"doctorInCharge": [
		{
			"name": "Ho Chee Khun",
			"qualifications": [
				"MBBS (University of Malaya, Malaysia) 1989",
				"MRCP (UK) (Royal College of Physicians, United Kingdom) 1994"
			],
			"specialties": [
				"Renal Medicine"
			]
		}
	],
	"mohApprovedSpecialServices": [
		"Renal Dialysis"
	],
	"detailedServices": {
		"Specialist Medical": [
			"Renal Medicine"
		]
	},
	"id": "14M0270",
	"coordinates": [
		103.804019,
		1.2868513
	],
	"svy21": [
		24739.21,
		29919.02
	],
	"planningArea": "BM",
	"neighbours": [
		"QT",
		"TN",
		"SI",
		"CA"
	]
}