{
	"name": "UNICARE FAMILY CLINIC & SURGERY",
	"tel": "62660196",
	"fax": "65663770",
	"licensee": "UNICARE FAMILY CLINIC AND SURGERY PRIVATE LIMITED",
	"licensePeriod": "09/10/2017 to 08/10/2019",
	"licenseClass": "[ 2 Years ( 2A ) ]",
	"hciCode": "17M0316",
	"address": "BLK 216 BOON LAY AVENUE, MULTI STOREY CAR PARK, #01-03 Singapore 640216",
	"doctorInCharge": [
		{
			"name": "Lim Lee Min Dale",
			"qualifications": [
				"MBBS (National University of Singapore, Singapore) 1997"
			],
			"specialties": [
				"Aviation Medicine"
			]
		}
	],
	"detailedServices": {
		"General Medical": true
	},
	"id": "17M0316",
	"coordinates": [
		103.7117037,
		1.3496777
	],
	"svy21": [
		14465.62,
		36866.36
	],
	"planningArea": "JW",
	"neighbours": [
		"BL",
		"JE",
		"PN",
		"TH",
		"WC"
	]
}